supergrad/__init__.py
supergrad/version.py
supergrad/helper/__init__.py
supergrad/helper/compute_spectrum.py
supergrad/helper/compute_unitary_evolve.py
supergrad/helper/helper.py
supergrad/quantum_system/__init__.py
supergrad/quantum_system/artificial_atom.py
supergrad/quantum_system/base.py
supergrad/quantum_system/circuit.py
supergrad/quantum_system/interaction.py
supergrad/quantum_system/kronobj.py
supergrad/quantum_system/lindbladobj.py
supergrad/scgraph/__init__.py
supergrad/scgraph/graph.py
supergrad/scgraph/graph_mpc_fluxonium_1d.py
supergrad/scgraph/graph_mpc_fluxonium_5x5_periodic.py
supergrad/scgraph/graph_transmon_1d.py
supergrad/time_evolution/__init__.py
supergrad/time_evolution/lindblad_solver.py
supergrad/time_evolution/ode.py
supergrad/time_evolution/pulseshape.py
supergrad/time_evolution/schrodinger_solver.py
supergrad/time_evolution/single_qubit_compensation.py
supergrad/utils/__init__.py
supergrad/utils/docstring.py
supergrad/utils/fidelity.py
supergrad/utils/gates.py
supergrad/utils/latex.py
supergrad/utils/loss_function.py
supergrad/utils/memory_profiling.py
supergrad/utils/operators.py
supergrad/utils/optimize.py
supergrad/utils/progress_bar.py
supergrad/utils/qec.py
supergrad/utils/qiskit_interface.py
supergrad/utils/qutip_interface.py
supergrad/utils/sharding.py
supergrad/utils/sys_diagnose.py
supergrad/utils/utility.py
supergrad-0.2.6.dist-info/licenses/LICENSE
supergrad-0.2.6.dist-info/METADATA
supergrad-0.2.6.dist-info/WHEEL
supergrad-0.2.6.dist-info/top_level.txt
supergrad-0.2.6.dist-info/RECORD
