Metadata-Version: 2.4
Name: supergrad
Version: 0.2.6
Summary: SuperGrad differentiable Hamiltonian simulator
Home-page: https://github.com/iqubit-org/supergrad
Author: IQUBIT
License: Apache-2.0
Platform: any
Classifier: Programming Language :: Python :: 3.9
Classifier: Programming Language :: Python :: 3.10
Classifier: Programming Language :: Python :: 3.11
Classifier: Operating System :: OS Independent
Requires-Python: >=3.9
License-File: LICENSE
Requires-Dist: numpy
Requires-Dist: scipy
Requires-Dist: matplotlib
Requires-Dist: jax
Requires-Dist: dm_haiku
Requires-Dist: jaxopt
Requires-Dist: networkx
Requires-Dist: tqdm
Requires-Dist: rich
Provides-Extra: benchmark
Requires-Dist: qiskit_dynamics; extra == "benchmark"
Requires-Dist: qiskit<2.0; extra == "benchmark"
Requires-Dist: qutip; extra == "benchmark"
Requires-Dist: pytest; extra == "benchmark"
Requires-Dist: pytest-benchmark; extra == "benchmark"
Requires-Dist: scqubits; extra == "benchmark"
Requires-Dist: psutil; extra == "benchmark"
Provides-Extra: docs
Requires-Dist: qutip; extra == "docs"
Requires-Dist: qutip-qip; extra == "docs"
Provides-Extra: latex
Requires-Dist: pylatex; extra == "latex"
Dynamic: author
Dynamic: classifier
Dynamic: description
Dynamic: description-content-type
Dynamic: home-page
Dynamic: license
Dynamic: license-file
Dynamic: platform
Dynamic: provides-extra
Dynamic: requires-dist
Dynamic: requires-python
Dynamic: summary
